esp32-api-001/DataChangeUtil.py
esp32-api-001/FactoryUtil.py
esp32-api-001/FlagCode.py
esp32-api-001/Main.py
esp32-api-001/ReturnDataSubstring.py
esp32-api-001/__init__.py
esp32api/DataChangeUtil.py
esp32api/FactoryUtil.py
esp32api/FlagCode.py
esp32api/Main.py
esp32api/ReturnDataSubstring.py
esp32api/__init__.py
esp32api-0.0.1.dist-info/LICENSE
esp32api-0.0.1.dist-info/METADATA
esp32api-0.0.1.dist-info/WHEEL
esp32api-0.0.1.dist-info/top_level.txt
esp32api-0.0.1.dist-info/RECORD
