Metadata-Version: 2.1
Name: esp32api
Version: 0.0.1
Summary: A small example package
Home-page: https://github.com/yourusername/mypymodule
Author: AL
Author-email: AL <zhoulong0014@163.com>
Project-URL: Homepage, https://github.com/pypa/sampleproject
Project-URL: Issues, https://github.com/pypa/sampleproject/issues
Classifier: Programming Language :: Python :: 3
Classifier: License :: OSI Approved :: MIT License
Classifier: Operating System :: OS Independent
Requires-Python: >=3.6
License-File: LICENSE
